CHANGELOG
MANIFEST.in
README.rst
conf.py
index.rst
setup.cfg
setup.py
dropbox/Makefile
dropbox/__init__.py
dropbox/__init__.pyc
dropbox/client.py
dropbox/client.pyc
dropbox/metadata.py
dropbox/metadata.pyc
dropbox/rest.py
dropbox/rest.pyc
dropbox/session.py
dropbox/session.pyc
dropbox/six.py
dropbox/six.pyc
dropbox/trusted-certs.crt
dropbox/util.py
dropbox/util.pyc
dropbox2.egg-info/PKG-INFO
dropbox2.egg-info/SOURCES.txt
dropbox2.egg-info/dependency_links.txt
dropbox2.egg-info/requires.txt
dropbox2.egg-info/top_level.txt
testfiles/Costa Rican Frog.jpg
testfiles/dropbox_song.mp3
testfiles/foo.txt
tests/__init__.py
tests/__init__.pyc
tests/server.crt
tests/server.key
tests/test_client.py
tests/test_client.pyc
tests/test_rest.py
tests/test_session.py