Metadata-Version: 1.0
Name: dropbox2
Version: 1.7.1
Summary: Dropbox REST API Client with more consistent responses.
Home-page: http://wol.ph/
Author: Rick van Hattem
Author-email: Rick@Wol.ph
License: UNKNOWN
Platform: UNKNOWN
